fake_useragent/__init__.py
fake_useragent/errors.py
fake_useragent/fake.py
fake_useragent/log.py
fake_useragent/settings.py
fake_useragent/utils.py
tests/__init__.py
tests/conftest.py
tests/test_errors.py
tests/test_fake.py
tests/test_utils.py
tests/utils.py
tests/assets/no_browser_versions.html
alt_fake_useragent-0.2.1.dist-info/AUTHORS.md
alt_fake_useragent-0.2.1.dist-info/LICENSE
alt_fake_useragent-0.2.1.dist-info/METADATA
alt_fake_useragent-0.2.1.dist-info/WHEEL
alt_fake_useragent-0.2.1.dist-info/top_level.txt
alt_fake_useragent-0.2.1.dist-info/RECORD
