Metadata-Version: 2.1
Name: alt-fake-useragent
Version: 0.2.1
Summary: A Fixed and Updated Alternative for fake-useragent
Home-page: https://github.com/MrBotDeveloper/Fake-UserAgent-Alternate
Author: botmakerdeveloper@gmail.com
Author-email: botmakerdeveloper@gmail.com
License: UNKNOWN
Keywords: user,agent,user agent,useragent,fake,alternate fake useragent,fake user agent,fixed fake useragent,python requests
Platform: UNKNOWN
Classifier: Development Status :: 5 - Production/Stable
Classifier: Intended Audience :: Developers
Classifier: License :: OSI Approved :: Apache Software License
Classifier: Operating System :: POSIX
Classifier: Operating System :: MacOS :: MacOS X
Classifier: Operating System :: Microsoft :: Windows
Classifier: Programming Language :: Python
Classifier: Programming Language :: Python :: 2
Classifier: Programming Language :: Python :: 3
Classifier: Operating System :: OS Independent
License-File: LICENSE
License-File: AUTHORS.md
